{"530107": 
{ "name": "삼성 인버스 2X 코스닥150 선물 ETN"
, "symbol": "530107.KS"
, "interval": "1wk"
, "rows": 1
, "last_bar_start": "2026-04-13T00:00:00"
, "last_bar_end": "2026-04-14T00:00:00"
, "profile": {"1713": 4184692, "1790": 4184692, "1785": 2789795, "1721": 2789795}
, "price_set": [1713, 1721, 1785, 1790]
, "energies": [24006.183]
, "ohlcv": 
{ "ts": [1776038400000]
, "open": [1785.0]
, "high": [1790.0]
, "low": [1713.0]
, "close": [1721.0]
, "volume": [13948973]}}, "530134": 
{ "name": "삼성 블룸버그 인버스2X WTI원유선물 ETN B"
, "symbol": "530134.KS"
, "interval": "1wk"
, "rows": 1
, "last_bar_start": "2026-04-13T00:00:00"
, "last_bar_end": "2026-04-14T00:00:00"
, "profile": {"3225": 889777, "3335": 889777, "3230": 593185, "3290": 593185}
, "price_set": [3225, 3230, 3290, 3335]
, "energies": [9757.887]
, "ohlcv": 
{ "ts": [1776038400000]
, "open": [3230.0]
, "high": [3335.0]
, "low": [3225.0]
, "close": [3290.0]
, "volume": [2965923]}}}